{
    "message": "成功",
    "status": 1,
    "data": {
        "total": 69,
        "estateSubList": [
            {
                "id": 77,
                "estateId": 17652,
                "subEstateId": 113393,
                "subEstateName": null,
                "estateName": "东湾小区",
                "townid": 3608,
                "townStr": "上海市-徐汇区-华泾",
                "townidDesc": null,
                "totalHouse": null,
                "volumeRate": null,
                "greenRate": null,
                "propertyCharges": null,
                "propertyType": null,
                "propertyTypeStr": null,
                "propertyCompany": null,
                "propertyRight": null,
                "developers": null,
                "completed": null,
                "businessCycle": null,
                "traffic": null,
                "bank": null,
                "hospital": null,
                "agentId": 19295,
                "publishName": "777",
                "operatorId": null,
                "checkStatus": 2,
                "checkStatusStr": "待审核",
                "status": null,
                "createTime": null,
                "createTimeStr": "2016-12-13 11:41",
                "updateTime": 1481600478000,
                "note": null,
                "estateImageResponses": null
            },
            {
                "id": 76,
                "estateId": 16391,
                "subEstateId": 12320,
                "subEstateName": null,
                "estateName": "伦敦广场",
                "townid": 4442,
                "townStr": "上海市-长宁区-古北区",
                "townidDesc": null,
                "totalHouse": null,
                "volumeRate": null,
                "greenRate": null,
                "propertyCharges": null,
                "propertyType": null,
                "propertyTypeStr": null,
                "propertyCompany": null,
                "propertyRight": null,
                "developers": null,
                "completed": null,
                "businessCycle": null,
                "traffic": null,
                "bank": null,
                "hospital": null,
                "agentId": 19295,
                "publishName": "777",
                "operatorId": null,
                "checkStatus": 2,
                "checkStatusStr": "待审核",
                "status": null,
                "createTime": null,
                "createTimeStr": "2016-12-13 11:40",
                "updateTime": 1481600411000,
                "note": null,
                "estateImageResponses": null
            },
            {
                "id": 75,
                "estateId": 16426,
                "subEstateId": 12355,
                "subEstateName": null,
                "estateName": "马赛花园（东）",
                "townid": 4442,
                "townStr": "上海市-长宁区-古北区",
                "townidDesc": null,
                "totalHouse": null,
                "volumeRate": null,
                "greenRate": null,
                "propertyCharges": null,
                "propertyType": null,
                "propertyTypeStr": null,
                "propertyCompany": null,
                "propertyRight": null,
                "developers": null,
                "completed": null,
                "businessCycle": null,
                "traffic": null,
                "bank": null,
                "hospital": null,
                "agentId": 19020,
                "publishName": "王思",
                "operatorId": null,
                "checkStatus": 2,
                "checkStatusStr": "待审核",
                "status": null,
                "createTime": null,
                "createTimeStr": "2016-12-08 03:50",
                "updateTime": 1481183405000,
                "note": null,
                "estateImageResponses": null
            },
            {
                "id": 74,
                "estateId": 16815,
                "subEstateId": 12744,
                "subEstateName": null,
                "estateName": "三乐小区",
                "townid": 3814,
                "townStr": "上海市-静安区-江宁路",
                "townidDesc": null,
                "totalHouse": null,
                "volumeRate": null,
                "greenRate": null,
                "propertyCharges": null,
                "propertyType": null,
                "propertyTypeStr": null,
                "propertyCompany": null,
                "propertyRight": null,
                "developers": null,
                "completed": null,
                "businessCycle": null,
                "traffic": null,
                "bank": null,
                "hospital": null,
                "agentId": 19020,
                "publishName": "王思",
                "operatorId": null,
                "checkStatus": 2,
                "checkStatusStr": "待审核",
                "status": null,
                "createTime": null,
                "createTimeStr": "2016-12-06 04:30",
                "updateTime": 1481013027000,
                "note": null,
                "estateImageResponses": null
            },
            {
                "id": 73,
                "estateId": 16619,
                "subEstateId": 12548,
                "subEstateName": null,
                "estateName": "良友大楼",
                "townid": 3814,
                "townStr": "上海市-静安区-江宁路",
                "townidDesc": null,
                "totalHouse": null,
                "volumeRate": null,
                "greenRate": null,
                "propertyCharges": null,
                "propertyType": null,
                "propertyTypeStr": null,
                "propertyCompany": null,
                "propertyRight": null,
                "developers": null,
                "completed": null,
                "businessCycle": null,
                "traffic": null,
                "bank": null,
                "hospital": null,
                "agentId": 19020,
                "publishName": "王思",
                "operatorId": null,
                "checkStatus": 2,
                "checkStatusStr": "待审核",
                "status": null,
                "createTime": null,
                "createTimeStr": "2016-12-06 04:27",
                "updateTime": 1481012831000,
                "note": null,
                "estateImageResponses": null
            },
            {
                "id": 72,
                "estateId": 18724,
                "subEstateId": 14653,
                "subEstateName": null,
                "estateName": "长虹小区",
                "townid": 3625,
                "townStr": "上海市-长宁区-新华路",
                "townidDesc": null,
                "totalHouse": null,
                "volumeRate": null,
                "greenRate": null,
                "propertyCharges": null,
                "propertyType": null,
                "propertyTypeStr": null,
                "propertyCompany": null,
                "propertyRight": null,
                "developers": null,
                "completed": null,
                "businessCycle": null,
                "traffic": null,
                "bank": null,
                "hospital": null,
                "agentId": 19317,
                "publishName": "管乐",
                "operatorId": null,
                "checkStatus": 2,
                "checkStatusStr": "待审核",
                "status": null,
                "createTime": null,
                "createTimeStr": "2016-12-06 02:20",
                "updateTime": 1481005203000,
                "note": null,
                "estateImageResponses": null
            },
            {
                "id": 71,
                "estateId": 40064,
                "subEstateId": 38075,
                "subEstateName": null,
                "estateName": "大通花园",
                "townid": 4470,
                "townStr": "苏州市-姑苏-桃花坞",
                "townidDesc": null,
                "totalHouse": null,
                "volumeRate": null,
                "greenRate": null,
                "propertyCharges": null,
                "propertyType": null,
                "propertyTypeStr": null,
                "propertyCompany": null,
                "propertyRight": null,
                "developers": null,
                "completed": null,
                "businessCycle": null,
                "traffic": null,
                "bank": null,
                "hospital": null,
                "agentId": 19115,
                "publishName": "尹",
                "operatorId": null,
                "checkStatus": 2,
                "checkStatusStr": "待审核",
                "status": null,
                "createTime": null,
                "createTimeStr": "2016-12-06 11:29",
                "updateTime": 1480994951000,
                "note": null,
                "estateImageResponses": null
            },
            {
                "id": 70,
                "estateId": 16430,
                "subEstateId": 12359,
                "subEstateName": null,
                "estateName": "皇家花园新虹桥绿景园",
                "townid": 4442,
                "townStr": "上海市-长宁区-古北区",
                "townidDesc": null,
                "totalHouse": null,
                "volumeRate": null,
                "greenRate": null,
                "propertyCharges": null,
                "propertyType": null,
                "propertyTypeStr": null,
                "propertyCompany": null,
                "propertyRight": null,
                "developers": null,
                "completed": null,
                "businessCycle": null,
                "traffic": null,
                "bank": null,
                "hospital": null,
                "agentId": 19233,
                "publishName": "亚索",
                "operatorId": null,
                "checkStatus": 2,
                "checkStatusStr": "待审核",
                "status": null,
                "createTime": null,
                "createTimeStr": "2016-12-03 10:34",
                "updateTime": 1480732470000,
                "note": null,
                "estateImageResponses": null
            },
            {
                "id": 69,
                "estateId": 17169,
                "subEstateId": 13098,
                "subEstateName": null,
                "estateName": "宏润国际花园",
                "townid": 3614,
                "townStr": "上海市-徐汇区-万体馆",
                "townidDesc": null,
                "totalHouse": null,
                "volumeRate": null,
                "greenRate": null,
                "propertyCharges": null,
                "propertyType": null,
                "propertyTypeStr": null,
                "propertyCompany": null,
                "propertyRight": null,
                "developers": null,
                "completed": null,
                "businessCycle": null,
                "traffic": null,
                "bank": null,
                "hospital": null,
                "agentId": 14308,
                "publishName": "孙大圣",
                "operatorId": null,
                "checkStatus": 2,
                "checkStatusStr": "待审核",
                "status": null,
                "createTime": null,
                "createTimeStr": "2016-12-01 01:58",
                "updateTime": 1480571918000,
                "note": null,
                "estateImageResponses": null
            },
            {
                "id": 68,
                "estateId": 17178,
                "subEstateId": 13107,
                "subEstateName": null,
                "estateName": "正南花苑",
                "townid": 3612,
                "townStr": "上海市-徐汇区-上海南站",
                "townidDesc": null,
                "totalHouse": null,
                "volumeRate": null,
                "greenRate": null,
                "propertyCharges": null,
                "propertyType": null,
                "propertyTypeStr": null,
                "propertyCompany": null,
                "propertyRight": null,
                "developers": null,
                "completed": null,
                "businessCycle": null,
                "traffic": null,
                "bank": null,
                "hospital": null,
                "agentId": 14308,
                "publishName": "孙大圣",
                "operatorId": null,
                "checkStatus": 2,
                "checkStatusStr": "待审核",
                "status": null,
                "createTime": null,
                "createTimeStr": "2016-12-01 01:57",
                "updateTime": 1480571822000,
                "note": null,
                "estateImageResponses": null
            }
        ],
        "page": 1
    }
}